{
  "business_id": "8234643",
  "business_name": "FIRST IMPRESSION CLEANING & RESTORATION SOLUTIONS L.L.C.",
  "type": "Domestic Limited Liability Company",
  "formation_date": "03/16/2016",
  "jurisdiction": "Kansas",
  "status": "success",
  "resident_agent": "JAMES C BARFIELD",
  "last_reporting_year": "",
  "next_report_due_date": "04/15/2017",
  "forfeiture_date": "07/15/2017",
  "principal_office_address": "2131  Edgemoor | WICHITA, KS 67208",
  "registered_office_address": "2131  Edgemoor | WICHITA, KS 67208",
  "search_term": "LLC",
  "extracted_at": "2025-11-28T22:59:16.365455"
}